proxyauth/__init__.py
proxyauth/auth/__init__.py
proxyauth/auth/auth.py
proxyauth/auth/server.py
proxyauth/auth/user_store.py
proxyauth/auth/static/__init__.py
proxyauth/auth/templates/__init__.py
proxyauth/auth/templates/signin.html
proxyauth/auth/templates/signup.html
proxyauth/auth/templates/signuped.html
proxyauth/proxy/__init__.py
proxyauth/proxy/server.py
proxyauth-2018.8.3.dist-info/METADATA
proxyauth-2018.8.3.dist-info/RECORD
proxyauth-2018.8.3.dist-info/WHEEL
proxyauth-2018.8.3.dist-info/top_level.txt
