Metadata-Version: 2.1
Name: proxyauth
Version: 2018.8.3
Summary: simple proxy auth for python app
Home-page: https://github.com/pingf/proxyauth.git
Author: Jesse MENG
Author-email: pingf0@gmail.com
License: MIT
Platform: any
Classifier: Intended Audience :: Developers
Classifier: License :: OSI Approved :: MIT License
Classifier: Operating System :: OS Independent
Classifier: Programming Language :: Python
Classifier: Topic :: Software Development :: Libraries :: Python Modules
Requires-Dist: flask
Requires-Dist: bcrypt
Requires-Dist: requests
Requires-Dist: store
